{
	"2019-10-28 08:30:00": [

	],
	"2019-10-28 11:00:00": [

	],
	"2019-10-28 13:30:00": [
		{
            "CourseID": "KEN1220",
            "Name": "Introduction to Computer Science 2",
            "ProgID": "BAY1",
            "RoomID": "TAPB 0.009",
            "Lecturers": "E.Smirnov;A.Zarras"
        },
		{
            "CourseID": "KEN1410",
            "Name": "Linear Algebra",
            "ProgID": "BAY1",
            "RoomID": "TAPB 0.004",
            "Lecturers": "P.Bonizzi;S.Mehrkanoon"
        }
	],
	"2019-10-28 16:00:00": [
		{
            "CourseID": "KEN1220",
            "Name": "Introduction to Computer Science 2",
            "ProgID": "BAY1",
            "RoomID": "TAPB 0.004",
            "Lecturers": "E.Smirnov;A.Zarras"
        },
		{
            "CourseID": "KEN1410",
            "Name": "Linear Algebra",
            "ProgID": "BAY1",
            "RoomID": "TAPB 0.009",
            "Lecturers": "P.Bonizzi;S.Mehrkanoon"
        }
	],

	"2019-10-29 08:30:00": [
		{
            "CourseID": "KEN1210",
            "Name": "Computational and Cognitive Neuroscience",
            "ProgID": "BAY1",
            "RoomID": "Pathe Hall 8",
            "Lecturers": "A.Roebroeck;M.Capalbo"
        }
	],
	"2019-10-29 11:00:00": [
		{
            "CourseID": "KEN1300-1",
            "Name": "Project Meeting",
            "ProgID": "BAY1",
            "RoomID": "BOU 0.009",
            "Lecturers": "K.Schüller;M.Popa;C.Sironi"
        }
	],
	"2019-10-29 13:30:00": [
		{
            "CourseID": "KEN1300-1",
            "Name": "Project Meeting",
            "ProgID": "BAY1",
            "RoomID": "BOU 0.009",
            "Lecturers": "K.Schüller;M.Popa;C.Sironi"
        }
	],
	"2019-10-29 16:00:00": [
		{
            "CourseID": "KEN1300-1",
            "Name": "Project Meeting",
            "ProgID": "BAY1",
            "RoomID": "BOU 0.009",
            "Lecturers": "K.Schüller;M.Popa;C.Sironi"
        }
	],

	"2019-10-30 08:30:00": [
		{
            "CourseID": "KEN1410",
            "Name": "Linear Algebra",
            "ProgID": "BAY1",
            "RoomID": "TAPB 0.009",
            "Lecturers": "P.Bonizzi;S.Mehrkanoon"
        }
	],
	"2019-10-30 11:00:00": [
		{
            "CourseID": "KEN1410",
            "Name": "Linear Algebra",
            "ProgID": "BAY1",
            "RoomID": "TAPB 0.009",
            "Lecturers": "P.Bonizzi;S.Mehrkanoon"
        },
		{
            "CourseID": "KEN2300-1",
            "Name": "Project Meeting",
            "ProgID": "BAY2",
            "RoomID": "BOU 2.015",
            "Lecturers": "K.Schüller"
        },
		{
            "CourseID": "KEN4154",
            "Name": "Advanced Concepts in Machine Learning",
            "ProgID": "MAAIDSDM",
            "RoomID": "TAPZ 0.011",
            "Lecturers": "K.Driessens;D.Rafailidis"
        }
	],
	"2019-10-30 13:30:00": [
		{
            "CourseID": "KEN2300-1",
            "Name": "Project Meeting",
            "ProgID": "BAY2",
            "RoomID": "BOU 2.015",
            "Lecturers": "K.Schüller"
        },
		{
            "CourseID": "KEN4154",
            "Name": "Advanced Concepts in Machine Learning",
            "ProgID": "MAAIDSDM",
            "RoomID": "TAPZ 0.011",
            "Lecturers": "K.Driessens;D.Rafailidis"
        }
	],
	"2019-10-30 16:00:00": [
	    {
            "CourseID": "KEN3300-1",
            "Name": "Project Meeting",
            "ProgID": "BAY3",
            "RoomID": "BOU 0.009",
            "Lecturers": "R.Möckel"
        },
        {
            "CourseID": "KEN4111",
            "Name": "Multi-Agent Systems",
            "ProgID": "MAAIDSDM",
            "RoomID": "BOU 1.001",
            "Lecturers": "G.Weiss"
        }
	],

	"2019-10-31 08:30:00": [
		{
            "CourseID": "KEN3440",
            "Name": "Introduction to Bio-Informatics",
            "ProgID": "BAY3",
            "RoomID": "BOU 0.015",
            "Lecturers": "R.Cavill"
        }
	],
	"2019-10-31 11:00:00": [
		{
            "CourseID": "KEN3440",
            "Name": "Introduction to Bio-Informatics",
            "ProgID": "BAY3",
            "RoomID": "BOU 0.015",
            "Lecturers": "R.Cavill"
        }
	],
	"2019-10-31 13:30:00": [
		{
            "CourseID": "KEN1410",
            "Name": "Linear Algebra",
            "ProgID": "BAY1",
            "RoomID": "TAPB 0.009",
            "Lecturers": "P.Bonizzi;S.Mehrkanoon"
        },
		{
            "CourseID": "KEN3150",
            "Name": "Software and Systems Verifications",
            "ProgID": "BAY3",
            "RoomID": "BOU 0.015",
            "Lecturers": "P.Collins"
        },
		{
            "CourseID": "KEN4245",
            "Name": "Information Security",
            "ProgID": "MAAIDSDM",
            "RoomID": "BOU 2.015",
            "Lecturers": "A.Zarras"
        }
	],
	"2019-10-31 16:00:00": [
		{
            "CourseID": "KEN1410",
            "Name": "Linear Algebra",
            "ProgID": "BAY1",
            "RoomID": "TAPB 0.009",
            "Lecturers": "P.Bonizzi;S.Mehrkanoon"
        },
		{
            "CourseID": "KEN3231",
            "Name": "Logic for Artificial Intelligence",
            "ProgID": "BAY3",
            "RoomID": "BOU 0.015",
            "Lecturers": "N.Roos"
        },
		{
            "CourseID": "KEN4244",
            "Name": "Applications of Image & Video Processing",
            "ProgID": "MAAIDSDM",
            "RoomID": "BOU 2.015",
            "Lecturers": "A.Briassouli"
        }
	],

	"2019-11-01 08:30:00": [
		{
            "CourseID": "KEN1220",
            "Name": "Introduction to Computer Science 2",
            "ProgID": "BAY1",
            "RoomID": "TAPB 0.009",
            "Lecturers": "E.Smirnov;A.Zarras"
        },
		{
            "CourseID": "KEN3235",
            "Name": "Parallel Programming",
            "ProgID": "BAY3",
            "RoomID": "BOU 0.015",
            "Lecturers": "H.Pflug;B.Küppers;C.Terboven"
        }
	],
	"2019-11-01 11:00:00": [
		{
            "CourseID": "KEN1220",
            "Name": "Introduction to Computer Science 2",
            "ProgID": "BAY1",
            "RoomID": "TAPB 0.009",
            "Lecturers": "E.Smirnov;A.Zarras"
        },
		{
            "CourseID": "KEN2220",
            "Name": "Graph Theory",
            "ProgID": "BAY2",
            "RoomID": "TAPZ 0.011",
            "Lecturers": "M.Mihalak"
        },
		{
            "CourseID": "KEN3235",
            "Name": "Parallel Programming",
            "ProgID": "BAY3",
            "RoomID": "BOU 0.015",
            "Lecturers": "H.Pflug;B.Küppers;C.Terboven"
        },
		{
            "CourseID": "KEN4245",
            "Name": "Information Security",
            "ProgID": "MAAIDSDM",
            "RoomID": "BOU 2.015",
            "Lecturers": "A.Zarras"
        }
	],
	"2019-11-01 13:30:00": [
		{
            "CourseID": "KEN1220",
            "Name": "Introduction to Computer Science 2",
            "ProgID": "BAY1",
            "RoomID": "TAPB 0.009",
            "Lecturers": "E.Smirnov;A.Zarras"
        },
		{
            "CourseID": "KEN2220",
            "Name": "Graph Theory",
            "ProgID": "BAY2",
            "RoomID": "TAPZ 0.011",
            "Lecturers": "M.Mihalak"
        },
		{
            "CourseID": "KEN3235",
            "Name": "Parallel Programming",
            "ProgID": "BAY3",
            "RoomID": "BOU 0.015",
            "Lecturers": "H.Pflug;B.Küppers;C.Terboven"
        },
		{
            "CourseID": "KEN4245",
            "Name": "Information Security",
            "ProgID": "MAAIDSDM",
            "RoomID": "BOU 2.015",
            "Lecturers": "A.Zarras"
        }
	],
	"2019-11-01 16:00:00": [
		{
            "CourseID": "KEN3231",
            "Name": "Logic for Artificial Intelligence",
            "ProgID": "BAY3",
            "RoomID": "BOU 0.015",
            "Lecturers": "N.Roos"
        }
	],




	"2019-11-04 08:30:00": [
		{
            "CourseID": "KEN1220",
            "Name": "Introduction to Computer Science 2",
            "ProgID": "BAY1",
            "RoomID": "TAPB 0.004",
            "Lecturers": "E.Smirnov;A.Zarras"
        },
		{
            "CourseID": "KEN1410",
            "Name": "Linear Algebra",
            "ProgID": "BAY1",
            "RoomID": "TAPB 0.009",
            "Lecturers": "P.Bonizzi;S.Mehrkanoon"
        },
		{
            "CourseID": "KEN2230",
            "Name": "Reasoning Techniques",
            "ProgID": "BAY2",
            "RoomID": "TAPZ 0.011",
            "Lecturers": "J.Uiterwijk"
        },
		{
            "CourseID": "KEN3440",
            "Name": "Introduction to Bio-Informatics",
            "ProgID": "BAY3",
            "RoomID": "BOU 0.015",
            "Lecturers": "R.Cavill"
        }
	],
	"2019-11-04 11:00:00": [
		{
            "CourseID": "KEN1220",
            "Name": "Introduction to Computer Science 2",
            "ProgID": "BAY1",
            "RoomID": "TAPB 0.004",
            "Lecturers": "E.Smirnov;A.Zarras"
        },
		{
            "CourseID": "KEN1410",
            "Name": "Linear Algebra",
            "ProgID": "BAY1",
            "RoomID": "TAPB 0.009",
            "Lecturers": "P.Bonizzi;S.Mehrkanoon"
        },
		{
            "CourseID": "KEN2230",
            "Name": "Reasoning Techniques",
            "ProgID": "BAY2",
            "RoomID": "TAPZ 0.011",
            "Lecturers": "J.Uiterwijk"
        },
		{
            "CourseID": "KEN3440",
            "Name": "Introduction to Bio-Informatics",
            "ProgID": "BAY3",
            "RoomID": "BOU 0.015",
            "Lecturers": "R.Cavill"
        },
		{
            "CourseID": "KEN4111",
            "Name": "Multi-Agent Systems",
            "ProgID": "MAAIDSDM",
            "RoomID": "BOU 1.001",
            "Lecturers": "G.Weiss"
        }
	],
	"2019-11-04 13:30:00": [
		{
            "CourseID": "KEN1210",
            "Name": "Computational and Cognitive Neuroscience",
            "ProgID": "BAY1",
            "RoomID": "Pathe Hall 8",
            "Lecturers": "A.Roebroeck;M.Capalbo"
        },
		{
            "CourseID": "KEN2220",
            "Name": "Graph Theory",
            "ProgID": "BAY2",
            "RoomID": "TAPZ 0.011",
            "Lecturers": "M.Mihalak"
        },
		{
            "CourseID": "KEN4111",
            "Name": "Multi-Agent Systems",
            "ProgID": "MAAIDSDM",
            "RoomID": "BOU 1.001",
            "Lecturers": "G.Weiss"
        }
	],
	"2019-11-04 16:00:00": [
		{
            "CourseID": "KEN2240",
            "Name": "Machine Learning",
            "ProgID": "BAY2",
            "RoomID": "TAPZ 0.011",
            "Lecturers": "E.Smirnov;R.Möckel;E.Hortal"
        },
		{
            "CourseID": "KEN3231",
            "Name": "Logic for Artificial Intelligence",
            "ProgID": "BAY3",
            "RoomID": "BOU 0.015",
            "Lecturers": "N.Roos"
        },
		{
            "CourseID": "KEN4154",
            "Name": "Advanced Concepts in Machine Learning",
            "ProgID": "MAAIDSDM",
            "RoomID": "TAPB 0.009",
            "Lecturers": "K.Driessens;D.Rafailidis"
        }
	],

	"2019-11-05 08:30:00": [
		{
            "CourseID": "KEN1210",
            "Name": "Computational and Cognitive Neuroscience",
            "ProgID": "BAY1",
            "RoomID": "Pathe Hall 8",
            "Lecturers": "A.Roebroeck;M.Capalbo"
        },
		{
            "CourseID": "KEN4244",
            "Name": "Applications of Image & Video Processing",
            "ProgID": "MAAIDSDM",
            "RoomID": "BOU 2.015",
            "Lecturers": "A.Briassouli"
        }
	],
	"2019-11-05 11:00:00": [
		{
            "CourseID": "KEN1300-1",
            "Name": "Project Meeting",
            "ProgID": "BAY1",
            "RoomID": "BOU 0.009",
            "Lecturers": "K.Schüller;M.Popa;C.Sironi"
        },
		{
            "CourseID": "KEN2230",
            "Name": "Reasoning Techniques",
            "ProgID": "BAY2",
            "RoomID": "TAPZ 0.011",
            "Lecturers": "J.Uiterwijk"
        },
		{
            "CourseID": "KEN3150",
            "Name": "Software and Systems Verifications",
            "ProgID": "BAY3",
            "RoomID": "BOU 0.015",
            "Lecturers": "P.Collins"
        },
		{
            "CourseID": "KEN4244",
            "Name": "Applications of Image & Video Processing",
            "ProgID": "MAAIDSDM",
            "RoomID": "BOU 2.015",
            "Lecturers": "A.Briassouli"
        }
	],
	"2019-11-05 13:30:00": [
		{
            "CourseID": "KEN1300-1",
            "Name": "Project Meeting",
            "ProgID": "BAY1",
            "RoomID": "BOU 0.009",
            "Lecturers": "K.Schüller;M.Popa;C.Sironi"
        },
		{
            "CourseID": "KEN2240",
            "Name": "Machine Learning",
            "ProgID": "BAY2",
            "RoomID": "TAPZ 0.011",
            "Lecturers": "E.Smirnov;R.Möckel;E.Hortal"
        },
		{
            "CourseID": "KEN3150",
            "Name": "Software and Systems Verifications",
            "ProgID": "BAY3",
            "RoomID": "BOU 0.015",
            "Lecturers": "P.Collins"
        },
		{
            "CourseID": "KEN4242",
            "Name": "Model Identification and Data Fitting",
            "ProgID": "MAAIDSDM",
            "RoomID": "BOU 1.001",
            "Lecturers": "P.Bonizzi;R.Peeters"
        }
	],
	"2019-11-05 16:00:00": [
		{
            "CourseID": "KEN1300-1",
            "Name": "Project Meeting",
            "ProgID": "BAY1",
            "RoomID": "BOU 0.009",
            "Lecturers": "K.Schüller;M.Popa;C.Sironi"
        },
		{
            "CourseID": "KEN2240",
            "Name": "Machine Learning",
            "ProgID": "BAY2",
            "RoomID": "TAPZ 0.011",
            "Lecturers": "E.Smirnov;R.Möckel;E.Hortal"
        }
	],

	"2019-11-06 08:30:00": [
		{
            "CourseID": "KEN1410",
            "Name": "Linear Algebra",
            "ProgID": "BAY1",
            "RoomID": "TAPB 0.009",
            "Lecturers": "P.Bonizzi;S.Mehrkanoon"
        }
	],
	"2019-11-06 11:00:00": [
		{
            "CourseID": "KEN1410",
            "Name": "Linear Algebra",
            "ProgID": "BAY1",
            "RoomID": "TAPB 0.009",
            "Lecturers": "P.Bonizzi;S.Mehrkanoon"
        },
		{
            "CourseID": "KEN4154",
            "Name": "Advanced Concepts in Machine Learning",
            "ProgID": "MAAIDSDM",
            "RoomID": "TAPZ 0.011",
            "Lecturers": "K.Driessens;D.Rafailidis"
        }
	],
	"2019-11-06 13:30:00": [
		{
            "CourseID": "KEN1410",
            "Name": "Linear Algebra",
            "ProgID": "BAY1",
            "RoomID": "TAPB 0.009",
            "Lecturers": "P.Bonizzi;S.Mehrkanoon"
        },
		{
            "CourseID": "KEN3300-3",
            "Name": "Project Skills: CV workshop",
            "ProgID": "BAY3",
            "RoomID": "BON B1.31",
            "Lecturers": "SSC"
        },
		{
            "CourseID": "KEN4154",
            "Name": "Advanced Concepts in Machine Learning",
            "ProgID": "MAAIDSDM",
            "RoomID": "TAPZ 0.011",
            "Lecturers": "K.Driessens;D.Rafailidis"
        }
	],
	"2019-11-06 16:00:00": [
		{
            "CourseID": "KEN1410",
            "Name": "Linear Algebra",
            "ProgID": "BAY1",
            "RoomID": "TAPB 0.009",
            "Lecturers": "P.Bonizzi;S.Mehrkanoon"
        },
		{
            "CourseID": "KEN3300-1",
            "Name": "Project Meeting",
            "ProgID": "BAY3",
            "RoomID": "BOU 0.015",
            "Lecturers": "R.Möckel"
        },
		{
            "CourseID": "KEN4111",
            "Name": "Multi-Agent Systems",
            "ProgID": "MAAIDSDM",
            "RoomID": "BOU 1.001",
            "Lecturers": "G.Weiss"
        }
	],

	"2019-11-07 08:30:00": [
		{
            "CourseID": "KEN3440",
            "Name": "Introduction to Bio-Informatics",
            "ProgID": "BAY3",
            "RoomID": "BOU 0.015",
            "Lecturers": "R.Cavill"
        },
		{
            "CourseID": "KEN4242",
            "Name": "Model Identification and Data Fitting",
            "ProgID": "MAAIDSDM",
            "RoomID": "BOU 1.001",
            "Lecturers": "P.Bonizzi;R.Peeters"
        }
	],
	"2019-11-07 11:00:00": [
		{
            "CourseID": "KEN1210",
            "Name": "Computational and Cognitive Neuroscience",
            "ProgID": "BAY1",
            "RoomID": "TAPB 0.004",
            "Lecturers": "A.Roebroeck;M.Capalbo"
        },
		{
            "CourseID": "KEN3440",
            "Name": "Introduction to Bio-Informatics",
            "ProgID": "BAY3",
            "RoomID": "BOU 0.015",
            "Lecturers": "R.Cavill"
        },
		{
            "CourseID": "KEN4242",
            "Name": "Model Identification and Data Fitting",
            "ProgID": "MAAIDSDM",
            "RoomID": "BOU 1.001",
            "Lecturers": "P.Bonizzi;R.Peeters"
        }
	],
	"2019-11-07 13:30:00": [
		{
            "CourseID": "KEN1410",
            "Name": "Linear Algebra",
            "ProgID": "BAY1",
            "RoomID": "TAPB 0.009",
            "Lecturers": "P.Bonizzi;S.Mehrkanoon"
        },
		{
            "CourseID": "KEN3150",
            "Name": "Software and Systems Verifications",
            "ProgID": "BAY3",
            "RoomID": "BOU 0.015",
            "Lecturers": "P.Collins"
        },
		{
            "CourseID": "KEN4245",
            "Name": "Information Security",
            "ProgID": "MAAIDSDM",
            "RoomID": "BOU 2.015",
            "Lecturers": "A.Zarras"
        }
	],
	"2019-11-07 16:00:00": [
		{
            "CourseID": "KEN1410",
            "Name": "Linear Algebra",
            "ProgID": "BAY1",
            "RoomID": "TAPB 0.009",
            "Lecturers": "P.Bonizzi;S.Mehrkanoon"
        },
		{
            "CourseID": "KEN4244",
            "Name": "Applications of Image & Video Processing",
            "ProgID": "MAAIDSDM",
            "RoomID": "BOU 2.015",
            "Lecturers": "A.Briassouli"
        }
	],

	"2019-11-08 08:30:00": [
		{
            "CourseID": "KEN1220",
            "Name": "Introduction to Computer Science 2",
            "ProgID": "BAY1",
            "RoomID": "TAPB 0.009",
            "Lecturers": "E.Smirnov;A.Zarras"
        },
		{
            "CourseID": "KEN3235",
            "Name": "Parallel Programming",
            "ProgID": "BAY3",
            "RoomID": "BOU 0.015",
            "Lecturers": "H.Pflug;B.Küppers;C.Terboven"
        }
	],
	"2019-11-08 11:00:00": [
		{
            "CourseID": "KEN1220",
            "Name": "Introduction to Computer Science 2",
            "ProgID": "BAY1",
            "RoomID": "TAPB 0.009",
            "Lecturers": "E.Smirnov;A.Zarras"
        },
		{
            "CourseID": "KEN2220",
            "Name": "Graph Theory",
            "ProgID": "BAY2",
            "RoomID": "TAPZ 0.011",
            "Lecturers": "M.Mihalak"
        },
		{
            "CourseID": "KEN3235",
            "Name": "Parallel Programming",
            "ProgID": "BAY3",
            "RoomID": "BOU 0.015",
            "Lecturers": "H.Pflug;B.Küppers;C.Terboven"
        },
		{
            "CourseID": "KEN4245",
            "Name": "Information Security",
            "ProgID": "MAAIDSDM",
            "RoomID": "BOU 2.015",
            "Lecturers": "A.Zarras"
        }
	],
	"2019-11-08 13:30:00": [
		{
            "CourseID": "KEN1220",
            "Name": "Introduction to Computer Science 2",
            "ProgID": "BAY1",
            "RoomID": "TAPB 0.009",
            "Lecturers": "E.Smirnov;A.Zarras"
        },
		{
            "CourseID": "KEN2220",
            "Name": "Graph Theory",
            "ProgID": "BAY2",
            "RoomID": "TAPZ 0.011",
            "Lecturers": "M.Mihalak"
        },
		{
            "CourseID": "KEN3235",
            "Name": "Parallel Programming",
            "ProgID": "BAY3",
            "RoomID": "BOU 0.015",
            "Lecturers": "H.Pflug;B.Küppers;C.Terboven"
        },
		{
            "CourseID": "KEN4245",
            "Name": "Information Security",
            "ProgID": "MAAIDSDM",
            "RoomID": "BOU 2.015",
            "Lecturers": "A.Zarras"
        }
	],
	"2019-11-08 16:00:00": [

	],




	"2019-11-11 08:30:00": [
		{
            "CourseID": "KEN1220",
            "Name": "Introduction to Computer Science 2",
            "ProgID": "BAY1",
            "RoomID": "TAPB 0.009",
            "Lecturers": "E.Smirnov;A.Zarras"
        },
		{
            "CourseID": "KEN1410",
            "Name": "Linear Algebra",
            "ProgID": "BAY1",
            "RoomID": "TAPB 0.004",
            "Lecturers": "P.Bonizzi;S.Mehrkanoon"
        },
		{
            "CourseID": "KEN2230",
            "Name": "Reasoning Techniques",
            "ProgID": "BAY2",
            "RoomID": "TAPZ 0.011",
            "Lecturers": "J.Uiterwijk"
        },
		{
            "CourseID": "KEN3237",
            "Name": "Web Applications",
            "ProgID": "BAY3",
            "RoomID": "BOU 0.015",
            "Lecturers": "T.Dondorf"
        }
	],
	"2019-11-11 11:00:00": [
		{
            "CourseID": "KEN1220",
            "Name": "Introduction to Computer Science 2",
            "ProgID": "BAY1",
            "RoomID": "TAPB 0.004",
            "Lecturers": "E.Smirnov;A.Zarras"
        },
		{
            "CourseID": "KEN1410",
            "Name": "Linear Algebra",
            "ProgID": "BAY1",
            "RoomID": "TAPB 0.009",
            "Lecturers": "P.Bonizzi;S.Mehrkanoon"
        },
		{
            "CourseID": "KEN3237",
            "Name": "Web Applications",
            "ProgID": "BAY3",
            "RoomID": "BOU 0.015",
            "Lecturers": "T.Dondorf"
        },
		{
            "CourseID": "KEN4111",
            "Name": "Multi-Agent Systems",
            "ProgID": "MAAIDSDM",
            "RoomID": "BOU 1.001",
            "Lecturers": "G.Weiss"
        }
	],
	"2019-11-11 13:30:00": [
		{
            "CourseID": "KEN2220",
            "Name": "Graph Theory",
            "ProgID": "BAY2",
            "RoomID": "TAPZ 0.011",
            "Lecturers": "M.Mihalak"
        },
		{
            "CourseID": "KEN3237",
            "Name": "Web Applications",
            "ProgID": "BAY3",
            "RoomID": "BOU 0.015",
            "Lecturers": "T.Dondorf"
        },
		{
            "CourseID": "KEN4111",
            "Name": "Multi-Agent Systems",
            "ProgID": "MAAIDSDM",
            "RoomID": "BOU 1.001",
            "Lecturers": "G.Weiss"
        }
	],
	"2019-11-11 16:00:00": [
		{
            "CourseID": "KEN2240",
            "Name": "Machine Learning",
            "ProgID": "BAY2",
            "RoomID": "TAPZ 0.011",
            "Lecturers": "E.Smirnov;R.Möckel;E.Hortal"
        },
		{
            "CourseID": "KEN3231",
            "Name": "Logic for Artificial Intelligence",
            "ProgID": "BAY3",
            "RoomID": "BOU 0.015",
            "Lecturers": "N.Roos"
        },
		{
            "CourseID": "KEN4154",
            "Name": "Advanced Concepts in Machine Learning",
            "ProgID": "MAAIDSDM",
            "RoomID": "TAPB 0.009",
            "Lecturers": "K.Driessens;D.Rafailidis"
        }
	],

	"2019-11-12 08:30:00": [
		{
            "CourseID": "KEN1210",
            "Name": "Computational and Cognitive Neuroscience",
            "ProgID": "BAY1",
            "RoomID": "Pathe Hall 8",
            "Lecturers": "A.Roebroeck;M.Capalbo"
        },
		{
            "CourseID": "KEN2230",
            "Name": "Reasoning Techniques",
            "ProgID": "BAY2",
            "RoomID": "TAPZ 0.011",
            "Lecturers": "J.Uiterwijk"
        },
		{
            "CourseID": "KEN4244",
            "Name": "Applications of Image & Video Processing",
            "ProgID": "MAAIDSDM",
            "RoomID": "BOU 2.015",
            "Lecturers": "A.Briassouli"
        }
	],
	"2019-11-12 11:00:00": [
		{
            "CourseID": "KEN1300-4",
            "Name": "Project Skills: Information Research",
            "ProgID": "BAY1",
            "RoomID": "GL17 1.213 7A",
            "Lecturers": "R.Elands"
        },
		{
            "CourseID": "KEN2230",
            "Name": "Reasoning Techniques",
            "ProgID": "BAY2",
            "RoomID": "TAPZ 0.011",
            "Lecturers": "J.Uiterwijk"
        },
		{
            "CourseID": "KEN3150",
            "Name": "Software and Systems Verifications",
            "ProgID": "BAY3",
            "RoomID": "BOU 0.015",
            "Lecturers": "P.Collins"
        },
		{
            "CourseID": "KEN4244",
            "Name": "Applications of Image & Video Processing",
            "ProgID": "MAAIDSDM",
            "RoomID": "BOU 2.015",
            "Lecturers": "A.Briassouli"
        }
	],
	"2019-11-12 13:30:00": [
		{
            "CourseID": "KEN1300-4",
            "Name": "Project Skills: Information Research",
            "ProgID": "BAY1",
            "RoomID": "GL17 1.213 7A",
            "Lecturers": "R.Elands"
        },
		{
            "CourseID": "KEN2240",
            "Name": "Machine Learning",
            "ProgID": "BAY2",
            "RoomID": "TAPZ 0.011",
            "Lecturers": "E.Smirnov;R.Möckel;E.Hortal"
        },
		{
            "CourseID": "KEN3150",
            "Name": "Software and Systems Verifications",
            "ProgID": "BAY3",
            "RoomID": "BOU 0.015",
            "Lecturers": "P.Collins"
        },
		{
            "CourseID": "KEN4242",
            "Name": "Model Identification and Data Fitting",
            "ProgID": "MAAIDSDM",
            "RoomID": "BOU 1.001",
            "Lecturers": "P.Bonizzi;R.Peeters"
        }
	],
	"2019-11-12 16:00:00": [
		{
            "CourseID": "KEN2240",
            "Name": "Machine Learning",
            "ProgID": "BAY2",
            "RoomID": "TAPZ 0.011",
            "Lecturers": "E.Smirnov;R.Möckel;E.Hortal"
        },
		{
            "CourseID": "X1",
            "Name": "Details electives, study abroad, internship etc.",
            "ProgID": "MAAIDSDM",
            "RoomID": "BOU 1.001",
            "Lecturers": "T.Fox;W.Brandt"
        }
	],

	"2019-11-13 08:30:00": [

	],
	"2019-11-13 11:00:00": [

	],
	"2019-11-13 13:30:00": [
		{
            "CourseID": "KEN1410",
            "Name": "Linear Algebra",
            "ProgID": "BAY1",
            "RoomID": "TAPB 0.009",
            "Lecturers": "P.Bonizzi;S.Mehrkanoon"
        },
		{
            "CourseID": "KEN3300-3",
            "Name": "Project Skills: CV workshop",
            "ProgID": "BAY3",
            "RoomID": "BON B1.15",
            "Lecturers": "SSC"
        },
		{
            "CourseID": "KEN4154",
            "Name": "Advanced Concepts in Machine Learning",
            "ProgID": "MAAIDSDM",
            "RoomID": "TAPZ 0.011",
            "Lecturers": "K.Driessens;D.Rafailidis"
        }
	],
	"2019-11-13 16:00:00": [
		{
            "CourseID": "KEN1410",
            "Name": "Linear Algebra",
            "ProgID": "BAY1",
            "RoomID": "TAPB 0.009",
            "Lecturers": "P.Bonizzi;S.Mehrkanoon"
        },
		{
            "CourseID": "KEN3300-1",
            "Name": "Project Meeting",
            "ProgID": "BAY3",
            "RoomID": "BOU 0.009",
            "Lecturers": "R.Möckel"
        },
		{
            "CourseID": "KEN4154",
            "Name": "Advanced Concepts in Machine Learning",
            "ProgID": "MAAIDSDM",
            "RoomID": "TAPZ 0.011",
            "Lecturers": "K.Driessens;D.Rafailidis"
        }
	],

	"2019-11-14 08:30:00": [
		{
            "CourseID": "KEN1410",
            "Name": "Linear Algebra",
            "ProgID": "BAY1",
            "RoomID": "TAPB 0.004",
            "Lecturers": "P.Bonizzi;S.Mehrkanoon"
        },
		{
            "CourseID": "KEN1300-2",
            "Name": "Project Skills: Elementary Writing & Presenting",
            "ProgID": "BAY1",
            "RoomID": "TAPB 0.009",
            "Lecturers": "K.Schüller"
        },
		{
            "CourseID": "KEN3440",
            "Name": "Introduction to Bio-Informatics",
            "ProgID": "BAY3",
            "RoomID": "BOU 0.015",
            "Lecturers": "R.Cavill"
        },
		{
            "CourseID": "KEN4242",
            "Name": "Model Identification and Data Fitting",
            "ProgID": "MAAIDSDM",
            "RoomID": "BOU 1.001",
            "Lecturers": "P.Bonizzi;R.Peeters"
        }
	],
	"2019-11-14 11:00:00": [
		{
            "CourseID": "KEN1410",
            "Name": "Linear Algebra",
            "ProgID": "BAY1",
            "RoomID": "TAPB 0.009",
            "Lecturers": "P.Bonizzi;S.Mehrkanoon"
        },
		{
            "CourseID": "KEN1300-2",
            "Name": "Project Skills: Elementary Writing & Presenting",
            "ProgID": "BAY1",
            "RoomID": "TAPB 0.004",
            "Lecturers": "K.Schüller"
        },
		{
            "CourseID": "KEN3440",
            "Name": "Introduction to Bio-Informatics",
            "ProgID": "BAY3",
            "RoomID": "BOU 0.015",
            "Lecturers": "R.Cavill"
        },
		{
            "CourseID": "KEN4242",
            "Name": "Model Identification and Data Fitting",
            "ProgID": "MAAIDSDM",
            "RoomID": "BOU 1.001",
            "Lecturers": "P.Bonizzi;R.Peeters"
        }
	],
	"2019-11-14 13:30:00": [
		{
            "CourseID": "KEN1300-4",
            "Name": "Project Skills: Information Research",
            "ProgID": "BAY1",
            "RoomID": "GL17 1.213 7A",
            "Lecturers": "R.Elands"
        },
		{
            "CourseID": "KEN3150",
            "Name": "Software and Systems Verifications",
            "ProgID": "BAY3",
            "RoomID": "BOU 0.015",
            "Lecturers": "P.Collins"
        },
		{
            "CourseID": "KEN4245",
            "Name": "Information Security",
            "ProgID": "MAAIDSDM",
            "RoomID": "BOU 2.015",
            "Lecturers": "A.Zarras"
        }
	],
	"2019-11-14 16:00:00": [
		{
            "CourseID": "KEN4244",
            "Name": "Applications of Image & Video Processing",
            "ProgID": "MAAIDSDM",
            "RoomID": "BOU 2.015",
            "Lecturers": "A.Briassouli"
        }
	],

	"2019-11-15 08:30:00": [
		{
            "CourseID": "KEN1220",
            "Name": "Introduction to Computer Science 2",
            "ProgID": "BAY1",
            "RoomID": "TAPB 0.009",
            "Lecturers": "E.Smirnov;A.Zarras"
        },
		{
            "CourseID": "KEN2300-1",
            "Name": "Project Meeting",
            "ProgID": "BAY2",
            "RoomID": "BOU 0.009",
            "Lecturers": "K.Schüller"
        },
		{
            "CourseID": "KEN3235",
            "Name": "Parallel Programming",
            "ProgID": "BAY3",
            "RoomID": "BOU 0.015",
            "Lecturers": "H.Pflug;B.Küppers;C.Terboven"
        }
	],
	"2019-11-15 11:00:00": [
		{
            "CourseID": "KEN1220",
            "Name": "Introduction to Computer Science 2",
            "ProgID": "BAY1",
            "RoomID": "TAPB 0.009",
            "Lecturers": "E.Smirnov;A.Zarras"
        },
		{
            "CourseID": "KEN2300-1",
            "Name": "Project Meeting",
            "ProgID": "BAY2",
            "RoomID": "BOU 0.009",
            "Lecturers": "K.Schüller"
        },
		{
            "CourseID": "KEN3235",
            "Name": "Parallel Programming",
            "ProgID": "BAY3",
            "RoomID": "BOU 0.015",
            "Lecturers": "H.Pflug;B.Küppers;C.Terboven"
        },
		{
            "CourseID": "KEN4245",
            "Name": "Information Security",
            "ProgID": "MAAIDSDM",
            "RoomID": "BOU 2.015",
            "Lecturers": "A.Zarras"
        }
	],
	"2019-11-15 13:30:00": [
		{
            "CourseID": "KEN1220",
            "Name": "Introduction to Computer Science 2",
            "ProgID": "BAY1",
            "RoomID": "TAPB 0.009",
            "Lecturers": "E.Smirnov;A.Zarras"
        },
		{
            "CourseID": "KEN2220",
            "Name": "Graph Theory",
            "ProgID": "BAY2",
            "RoomID": "TAPZ 0.011",
            "Lecturers": "M.Mihalak"
        },
		{
            "CourseID": "KEN3235",
            "Name": "Parallel Programming",
            "ProgID": "BAY3",
            "RoomID": "BOU 0.015",
            "Lecturers": "H.Pflug;B.Küppers;C.Terboven"
        },
		{
            "CourseID": "KEN4245",
            "Name": "Information Security",
            "ProgID": "MAAIDSDM",
            "RoomID": "BOU 2.015",
            "Lecturers": "A.Zarras"
        }
	],
	"2019-11-15 16:00:00": [
		{
            "CourseID": "KEN3231",
            "Name": "Logic for Artificial Intelligence",
            "ProgID": "BAY3",
            "RoomID": "BOU 1.001",
            "Lecturers": "N.Roos"
        }
	],




	"2019-11-18 08:30:00": [
		{
            "CourseID": "KEN1220",
            "Name": "Introduction to Computer Science 2",
            "ProgID": "BAY1",
            "RoomID": "TAPB 0.009",
            "Lecturers": "E.Smirnov;A.Zarras"
        },
		{
            "CourseID": "KEN1410",
            "Name": "Linear Algebra",
            "ProgID": "BAY1",
            "RoomID": "TAPB 0.004",
            "Lecturers": "P.Bonizzi;S.Mehrkanoon"
        },
		{
            "CourseID": "KEN2230",
            "Name": "Reasoning Techniques",
            "ProgID": "BAY2",
            "RoomID": "TAPZ 0.011",
            "Lecturers": "J.Uiterwijk"
        },
		{
            "CourseID": "KEN3237",
            "Name": "Web Applications",
            "ProgID": "BAY3",
            "RoomID": "BOU 0.015",
            "Lecturers": "T.Dondorf"
        },
		{
            "CourseID": "X2",
            "Name": "Details electives, study abroad, internship etc.",
            "ProgID": "MAAIDSDM",
            "RoomID": "BOU 1.001",
            "Lecturers": "T.Fox;W.Brandt"
        }
	],
	"2019-11-18 11:00:00": [
		{
            "CourseID": "KEN1220",
            "Name": "Introduction to Computer Science 2",
            "ProgID": "BAY1",
            "RoomID": "TAPB 0.004",
            "Lecturers": "E.Smirnov;A.Zarras"
        },
		{
            "CourseID": "KEN1410",
            "Name": "Linear Algebra",
            "ProgID": "BAY1",
            "RoomID": "TAPB 0.009",
            "Lecturers": "P.Bonizzi;S.Mehrkanoon"
        },
		{
            "CourseID": "KEN2230",
            "Name": "Reasoning Techniques",
            "ProgID": "BAY2",
            "RoomID": "TAPZ 0.011",
            "Lecturers": "J.Uiterwijk"
        },
		{
            "CourseID": "KEN3237",
            "Name": "Web Applications",
            "ProgID": "BAY3",
            "RoomID": "BOU 0.015",
            "Lecturers": "T.Dondorf"
        },
		{
            "CourseID": "KEN4111",
            "Name": "Multi-Agent Systems",
            "ProgID": "MAAIDSDM",
            "RoomID": "BOU 1.001",
            "Lecturers": "G.Weiss"
        }
	],
	"2019-11-18 13:30:00": [
		{
            "CourseID": "KEN2240",
            "Name": "Machine Learning",
            "ProgID": "BAY2",
            "RoomID": "TAPZ 0.011",
            "Lecturers": "E.Smirnov;R.Möckel;E.Hortal"
        },
		{
            "CourseID": "KEN3237",
            "Name": "Web Applications",
            "ProgID": "BAY3",
            "RoomID": "BOU 0.015",
            "Lecturers": "T.Dondorf"
        },
		{
            "CourseID": "KEN4111",
            "Name": "Multi-Agent Systems",
            "ProgID": "MAAIDSDM",
            "RoomID": "BOU 1.001",
            "Lecturers": "G.Weiss"
        }
	],
	"2019-11-18 16:00:00": [
		{
            "CourseID": "KEN1210",
            "Name": "Computational and Cognitive Neuroscience",
            "ProgID": "BAY1",
            "RoomID": "TAPB 0.004",
            "Lecturers": "A.Roebroeck;M.Capalbo"
        },
		{
            "CourseID": "KEN2300-3",
            "Name": "Electives, minor, study abroad etc.",
            "ProgID": "BAY2",
            "RoomID": "TAPZ 0.011",
            "Lecturers": "T.Fox;W.Brandt"
        },
		{
            "CourseID": "KEN3231",
            "Name": "Logic for Artificial Intelligence",
            "ProgID": "BAY3",
            "RoomID": "BOU 0.015",
            "Lecturers": "N.Roos"
        },
		{
            "CourseID": "KEN4154",
            "Name": "Advanced Concepts in Machine Learning",
            "ProgID": "MAAIDSDM",
            "RoomID": "TAPB 0.009",
            "Lecturers": "K.Driessens;D.Rafailidis"
        }
	],

	"2019-11-19 08:30:00": [
		{
            "CourseID": "KEN1210",
            "Name": "Computational and Cognitive Neuroscience",
            "ProgID": "BAY1",
            "RoomID": "Pathe Hall 7",
            "Lecturers": "A.Roebroeck;M.Capalbo"
        },
		{
            "CourseID": "KEN2300-4",
            "Name": "Project Skills: Legal aspects of Data Science",
            "ProgID": "BAY2",
            "RoomID": "TAPZ 0.011",
            "Lecturers": "C.Monda;C.Mondschein"
        },
		{
            "CourseID": "KEN4244",
            "Name": "Applications of Image & Video Processing",
            "ProgID": "MAAIDSDM",
            "RoomID": "BOU 2.015",
            "Lecturers": "A.Briassouli"
        }
	],
	"2019-11-19 11:00:00": [
		{
            "CourseID": "KEN1300-1",
            "Name": "Project Meeting",
            "ProgID": "BAY1",
            "RoomID": "BOU 0.009",
            "Lecturers": "K.Schüller;M.Popa;C.Sironi"
        },
		{
            "CourseID": "KEN2230",
            "Name": "Reasoning Techniques",
            "ProgID": "BAY2",
            "RoomID": "TAPZ 0.011",
            "Lecturers": "J.Uiterwijk"
        },
		{
            "CourseID": "KEN3150",
            "Name": "Software and Systems Verifications",
            "ProgID": "BAY3",
            "RoomID": "BOU 0.015",
            "Lecturers": "P.Collins"
        },
		{
            "CourseID": "KEN4244",
            "Name": "Applications of Image & Video Processing",
            "ProgID": "MAAIDSDM",
            "RoomID": "BOU 2.015",
            "Lecturers": "A.Briassouli"
        }
	],
	"2019-11-19 13:30:00": [
		{
            "CourseID": "KEN1300-1",
            "Name": "Project Meeting",
            "ProgID": "BAY1",
            "RoomID": "BOU 0.009",
            "Lecturers": "K.Schüller;M.Popa;C.Sironi"
        },
		{
            "CourseID": "KEN2240",
            "Name": "Machine Learning",
            "ProgID": "BAY2",
            "RoomID": "TAPZ 0.011",
            "Lecturers": "E.Smirnov;R.Möckel;E.Hortal"
        },
		{
            "CourseID": "KEN3150",
            "Name": "Software and Systems Verifications",
            "ProgID": "BAY3",
            "RoomID": "BOU 0.015",
            "Lecturers": "P.Collins"
        },
		{
            "CourseID": "KEN4242",
            "Name": "Model Identification and Data Fitting",
            "ProgID": "MAAIDSDM",
            "RoomID": "BOU 1.001",
            "Lecturers": "P.Bonizzi;R.Peeters"
        }
	],
	"2019-11-19 16:00:00": [
		{
            "CourseID": "KEN1300-1",
            "Name": "Project Meeting",
            "ProgID": "BAY1",
            "RoomID": "BOU 0.009",
            "Lecturers": "K.Schüller;M.Popa;C.Sironi"
        },
		{
            "CourseID": "KEN2240",
            "Name": "Machine Learning",
            "ProgID": "BAY2",
            "RoomID": "TAPZ 0.011",
            "Lecturers": "E.Smirnov;R.Möckel;E.Hortal"
        }
	],

	"2019-11-20 08:30:00": [
		{
            "CourseID": "KEN1410",
            "Name": "Linear Algebra",
            "ProgID": "BAY1",
            "RoomID": "TAPB 0.009",
            "Lecturers": "P.Bonizzi;S.Mehrkanoon"
        },
		{
            "CourseID": "KEN2300-4",
            "Name": "Project Skills: Legal aspects of Data Science",
            "ProgID": "BAY2",
            "RoomID": "TAPZ 0.011",
            "Lecturers": "C.Monda;C.Mondschein"
        },
		{
            "CourseID": "KEN3300-3",
            "Name": "Project Skills: CV workshop",
            "ProgID": "BAY3",
            "RoomID": "BON B1.17",
            "Lecturers": "SSC"
        }
	],
	"2019-11-20 11:00:00": [
		{
            "CourseID": "KEN1410",
            "Name": "Linear Algebra",
            "ProgID": "BAY1",
            "RoomID": "TAPB 0.009",
            "Lecturers": "P.Bonizzi;S.Mehrkanoon"
        },
		{
            "CourseID": "KEN3300-3",
            "Name": "Project Skills: CV workshop",
            "ProgID": "BAY3",
            "RoomID": "BON B1.15",
            "Lecturers": "SSC"
        },
		{
            "CourseID": "KEN4154",
            "Name": "Advanced Concepts in Machine Learning",
            "ProgID": "MAAIDSDM",
            "RoomID": "TAPZ 0.011",
            "Lecturers": "K.Driessens;D.Rafailidis"
        }
	],
	"2019-11-20 13:30:00": [
		{
            "CourseID": "KEN1410",
            "Name": "Linear Algebra",
            "ProgID": "BAY1",
            "RoomID": "TAPB 0.009",
            "Lecturers": "P.Bonizzi;S.Mehrkanoon"
        },
		{
            "CourseID": "KEN3300-3",
            "Name": "Project Skills: CV workshop",
            "ProgID": "BAY3",
            "RoomID": "BON B1.31",
            "Lecturers": "SSC"
        },
		{
            "CourseID": "KEN4154",
            "Name": "Advanced Concepts in Machine Learning",
            "ProgID": "MAAIDSDM",
            "RoomID": "TAPZ 0.011",
            "Lecturers": "K.Driessens;D.Rafailidis"
        }
	],
	"2019-11-20 16:00:00": [
		{
            "CourseID": "KEN1410",
            "Name": "Linear Algebra",
            "ProgID": "BAY1",
            "RoomID": "TAPB 0.009",
            "Lecturers": "P.Bonizzi;S.Mehrkanoon"
        },
		{
            "CourseID": "KEN3300-1",
            "Name": "Project Meeting",
            "ProgID": "BAY3",
            "RoomID": "BOU 0.015",
            "Lecturers": "R.Möckel"
        },
		{
            "CourseID": "KEN4111",
            "Name": "Multi-Agent Systems",
            "ProgID": "MAAIDSDM",
            "RoomID": "BOU 1.001",
            "Lecturers": "G.Weiss"
        }
	],

	"2019-11-21 08:30:00": [
		{
            "CourseID": "KEN3440",
            "Name": "Introduction to Bio-Informatics",
            "ProgID": "BAY3",
            "RoomID": "BOU 0.015",
            "Lecturers": "R.Cavill"
        },
		{
            "CourseID": "KEN4242",
            "Name": "Model Identification and Data Fitting",
            "ProgID": "MAAIDSDM",
            "RoomID": "BOU 1.001",
            "Lecturers": "P.Bonizzi;R.Peeters"
        }
	],
	"2019-11-21 11:00:00": [
		{
            "CourseID": "KEN3440",
            "Name": "Introduction to Bio-Informatics",
            "ProgID": "BAY3",
            "RoomID": "BOU 0.015",
            "Lecturers": "R.Cavill"
        },
		{
            "CourseID": "KEN4242",
            "Name": "Model Identification and Data Fitting",
            "ProgID": "MAAIDSDM",
            "RoomID": "BOU 1.001",
            "Lecturers": "P.Bonizzi;R.Peeters"
        }
	],
	"2019-11-21 13:30:00": [
		{
            "CourseID": "KEN1410",
            "Name": "Linear Algebra",
            "ProgID": "BAY1",
            "RoomID": "TAPB 0.009",
            "Lecturers": "P.Bonizzi;S.Mehrkanoon"
        },
		{
            "CourseID": "KEN3150",
            "Name": "Software and Systems Verifications",
            "ProgID": "BAY3",
            "RoomID": "BOU 0.015",
            "Lecturers": "P.Collins"
        },
		{
            "CourseID": "KEN4245",
            "Name": "Information Security",
            "ProgID": "MAAIDSDM",
            "RoomID": "BOU 2.015",
            "Lecturers": "A.Zarras"
        }
	],
	"2019-11-21 16:00:00": [
		{
            "CourseID": "KEN1410",
            "Name": "Linear Algebra",
            "ProgID": "BAY1",
            "RoomID": "TAPB 0.009",
            "Lecturers": "P.Bonizzi;S.Mehrkanoon"
        },
		{
            "CourseID": "KEN3231",
            "Name": "Logic for Artificial Intelligence",
            "ProgID": "BAY3",
            "RoomID": "BOU 1.001",
            "Lecturers": "N.Roos"
        },
		{
            "CourseID": "KEN4244",
            "Name": "Applications of Image & Video Processing",
            "ProgID": "MAAIDSDM",
            "RoomID": "BOU 2.015",
            "Lecturers": "A.Briassouli"
        }
	],

	"2019-11-22 08:30:00": [
		{
            "CourseID": "KEN1220",
            "Name": "Introduction to Computer Science 2",
            "ProgID": "BAY1",
            "RoomID": "TAPB 0.009",
            "Lecturers": "E.Smirnov;A.Zarras"
        },
		{
            "CourseID": "KEN3235",
            "Name": "Parallel Programming",
            "ProgID": "BAY3",
            "RoomID": "BOU 1.001",
            "Lecturers": "H.Pflug;B.Küppers;C.Terboven"
        }
	],
	"2019-11-22 11:00:00": [
		{
            "CourseID": "KEN1220",
            "Name": "Introduction to Computer Science 2",
            "ProgID": "BAY1",
            "RoomID": "TAPB 0.009",
            "Lecturers": "E.Smirnov;A.Zarras"
        },
		{
            "CourseID": "KEN2220",
            "Name": "Graph Theory",
            "ProgID": "BAY2",
            "RoomID": "TAPZ 0.011",
            "Lecturers": "M.Mihalak"
        },
		{
            "CourseID": "KEN3235",
            "Name": "Parallel Programming",
            "ProgID": "BAY3",
            "RoomID": "BOU 1.001",
            "Lecturers": "H.Pflug;B.Küppers;C.Terboven"
        },
		{
            "CourseID": "KEN4245",
            "Name": "Information Security",
            "ProgID": "MAAIDSDM",
            "RoomID": "BOU 2.015",
            "Lecturers": "A.Zarras"
        }
	],
	"2019-11-22 13:30:00": [
		{
            "CourseID": "KEN1220",
            "Name": "Introduction to Computer Science 2",
            "ProgID": "BAY1",
            "RoomID": "TAPB 0.009",
            "Lecturers": "E.Smirnov;A.Zarras"
        },
		{
            "CourseID": "KEN2220",
            "Name": "Graph Theory",
            "ProgID": "BAY2",
            "RoomID": "TAPZ 0.011",
            "Lecturers": "M.Mihalak"
        },
		{
            "CourseID": "KEN3235",
            "Name": "Parallel Programming",
            "ProgID": "BAY3",
            "RoomID": "BOU 1.001",
            "Lecturers": "H.Pflug;B.Küppers;C.Terboven"
        },
		{
            "CourseID": "KEN4245",
            "Name": "Information Security",
            "ProgID": "MAAIDSDM",
            "RoomID": "BOU 2.015",
            "Lecturers": "A.Zarras"
        }
	],
	"2019-11-22 16:00:00": [
		{
            "CourseID": "KEN3231",
            "Name": "Logic for Artificial Intelligence",
            "ProgID": "BAY3",
            "RoomID": "BOU 1.001",
            "Lecturers": "N.Roos"
        }
	],




	"2019-11-25 08:30:00": [
		{
            "CourseID": "KEN1220",
            "Name": "Introduction to Computer Science 2",
            "ProgID": "BAY1",
            "RoomID": "TAPB 0.009",
            "Lecturers": "E.Smirnov;A.Zarras"
        },
		{
            "CourseID": "KEN1410",
            "Name": "Linear Algebra",
            "ProgID": "BAY1",
            "RoomID": "TAPB 0.004",
            "Lecturers": "P.Bonizzi;S.Mehrkanoon"
        },
		{
            "CourseID": "KEN3237",
            "Name": "Web Applications",
            "ProgID": "BAY3",
            "RoomID": "BOU 0.015",
            "Lecturers": "T.Dondorf"
        }
	],
	"2019-11-25 11:00:00": [
		{
            "CourseID": "KEN1220",
            "Name": "Introduction to Computer Science 2",
            "ProgID": "BAY1",
            "RoomID": "TAPB 0.004",
            "Lecturers": "E.Smirnov;A.Zarras"
        },
		{
            "CourseID": "KEN1410",
            "Name": "Linear Algebra",
            "ProgID": "BAY1",
            "RoomID": "TAPB 0.009",
            "Lecturers": "P.Bonizzi;S.Mehrkanoon"
        },
		{
            "CourseID": "KEN2230",
            "Name": "Reasoning Techniques",
            "ProgID": "BAY2",
            "RoomID": "TAPZ 0.011",
            "Lecturers": "J.Uiterwijk"
        },
		{
            "CourseID": "KEN3237",
            "Name": "Web Applications",
            "ProgID": "BAY3",
            "RoomID": "BOU 0.015",
            "Lecturers": "T.Dondorf"
        },
		{
            "CourseID": "KEN4111",
            "Name": "Multi-Agent Systems",
            "ProgID": "MAAIDSDM",
            "RoomID": "BOU 1.001",
            "Lecturers": "G.Weiss"
        }
	],
	"2019-11-25 13:30:00": [
		{
            "CourseID": "KEN2220",
            "Name": "Graph Theory",
            "ProgID": "BAY2",
            "RoomID": "TAPZ 0.011",
            "Lecturers": "M.Mihalak"
        },
		{
            "CourseID": "KEN3237",
            "Name": "Web Applications",
            "ProgID": "BAY3",
            "RoomID": "BOU 0.015",
            "Lecturers": "T.Dondorf"
        },
		{
            "CourseID": "KEN4111",
            "Name": "Multi-Agent Systems",
            "ProgID": "MAAIDSDM",
            "RoomID": "BOU 1.001",
            "Lecturers": "G.Weiss"
        }
	],
	"2019-11-25 16:00:00": [
		{
            "CourseID": "KEN2240",
            "Name": "Machine Learning",
            "ProgID": "BAY2",
            "RoomID": "TAPZ 0.011",
            "Lecturers": "E.Smirnov;R.Möckel;E.Hortal"
        },
		{
            "CourseID": "KEN3231",
            "Name": "Logic for Artificial Intelligence",
            "ProgID": "BAY3",
            "RoomID": "BOU 0.015",
            "Lecturers": "N.Roos"
        },
		{
            "CourseID": "KEN4154",
            "Name": "Advanced Concepts in Machine Learning",
            "ProgID": "MAAIDSDM",
            "RoomID": "TAPB 0.009",
            "Lecturers": "K.Driessens;D.Rafailidis"
        }
	],

	"2019-11-26 08:30:00": [
		{
            "CourseID": "KEN1210",
            "Name": "Computational and Cognitive Neuroscience",
            "ProgID": "BAY1",
            "RoomID": "Pathe Hall 8",
            "Lecturers": "A.Roebroeck;M.Capalbo"
        },
		{
            "CourseID": "KEN2230",
            "Name": "Reasoning Techniques",
            "ProgID": "BAY2",
            "RoomID": "TAPZ 0.011",
            "Lecturers": "J.Uiterwijk"
        },
		{
            "CourseID": "KEN4244",
            "Name": "Applications of Image & Video Processing",
            "ProgID": "MAAIDSDM",
            "RoomID": "BOU 2.015",
            "Lecturers": "A.Briassouli"
        }
	],
	"2019-11-26 11:00:00": [
		{
            "CourseID": "KEN1300-4",
            "Name": "Project Skills: Information Research",
            "ProgID": "BAY1",
            "RoomID": "GL17 1.213 7A",
            "Lecturers": "R.Elands"
        },
		{
            "CourseID": "KEN2230",
            "Name": "Reasoning Techniques",
            "ProgID": "BAY2",
            "RoomID": "TAPZ 0.011",
            "Lecturers": "J.Uiterwijk"
        },
		{
            "CourseID": "KEN3150",
            "Name": "Software and Systems Verifications",
            "ProgID": "BAY3",
            "RoomID": "BOU 0.015",
            "Lecturers": "P.Collins"
        },
		{
            "CourseID": "KEN4244",
            "Name": "Applications of Image & Video Processing",
            "ProgID": "MAAIDSDM",
            "RoomID": "BOU 2.015",
            "Lecturers": "A.Briassouli"
        }
	],
	"2019-11-26 13:30:00": [
		{
            "CourseID": "KEN1300-4",
            "Name": "Project Skills: Information Research",
            "ProgID": "BAY1",
            "RoomID": "GL17 1.213 7A",
            "Lecturers": "R.Elands"
        },
		{
            "CourseID": "KEN2240",
            "Name": "Machine Learning",
            "ProgID": "BAY2",
            "RoomID": "TAPZ 0.011",
            "Lecturers": "E.Smirnov;R.Möckel;E.Hortal"
        },
		{
            "CourseID": "KEN3150",
            "Name": "Software and Systems Verifications",
            "ProgID": "BAY3",
            "RoomID": "BOU 0.015",
            "Lecturers": "P.Collins"
        },
		{
            "CourseID": "KEN4242",
            "Name": "Model Identification and Data Fitting",
            "ProgID": "MAAIDSDM",
            "RoomID": "BOU 1.001",
            "Lecturers": "P.Bonizzi;R.Peeters"
        }
	],
	"2019-11-26 16:00:00": [
		{
            "CourseID": "KEN2240",
            "Name": "Machine Learning",
            "ProgID": "BAY2",
            "RoomID": "TAPZ 0.011",
            "Lecturers": "E.Smirnov;R.Möckel;E.Hortal"
        },
		{
            "CourseID": "KEN4242",
            "Name": "Model Identification and Data Fitting",
            "ProgID": "MAAIDSDM",
            "RoomID": "BOU 1.001",
            "Lecturers": "P.Bonizzi;R.Peeters"
        }
	],

	"2019-11-27 08:30:00": [
		{
            "CourseID": "KEN1410",
            "Name": "Linear Algebra",
            "ProgID": "BAY1",
            "RoomID": "TAPB 0.009",
            "Lecturers": "P.Bonizzi;S.Mehrkanoon"
        }
	],
	"2019-11-27 11:00:00": [
		{
            "CourseID": "KEN1410",
            "Name": "Linear Algebra",
            "ProgID": "BAY1",
            "RoomID": "TAPB 0.009",
            "Lecturers": "P.Bonizzi;S.Mehrkanoon"
        },
		{
            "CourseID": "KEN2300-1",
            "Name": "Project Meeting",
            "ProgID": "BAY2",
            "RoomID": "BOU 2.015",
            "Lecturers": "K.Schüller"
        },
		{
            "CourseID": "KEN4154",
            "Name": "Advanced Concepts in Machine Learning",
            "ProgID": "MAAIDSDM",
            "RoomID": "TAPZ 0.011",
            "Lecturers": "K.Driessens;D.Rafailidis"
        }
	],
	"2019-11-27 13:30:00": [
		{
            "CourseID": "KEN2300-1",
            "Name": "Project Meeting",
            "ProgID": "BAY2",
            "RoomID": "BOU 2.015",
            "Lecturers": "K.Schüller"
        },
		{
            "CourseID": "KEN4154",
            "Name": "Advanced Concepts in Machine Learning",
            "ProgID": "MAAIDSDM",
            "RoomID": "TAPZ 0.011",
            "Lecturers": "K.Driessens;D.Rafailidis"
        }
	],
	"2019-11-27 16:00:00": [
		{
            "CourseID": "KEN3300-1",
            "Name": "Project Meeting",
            "ProgID": "BAY3",
            "RoomID": "BOU 0.009",
            "Lecturers": "R.Möckel"
        },
		{
            "CourseID": "KEN4111",
            "Name": "Multi-Agent Systems",
            "ProgID": "MAAIDSDM",
            "RoomID": "BOU 1.001",
            "Lecturers": "G.Weiss"
        }
	],

	"2019-11-28 08:30:00": [
		{
            "CourseID": "KEN3440",
            "Name": "Introduction to Bio-Informatics",
            "ProgID": "BAY3",
            "RoomID": "BOU 0.015",
            "Lecturers": "R.Cavill"
        },
		{
            "CourseID": "KEN4242",
            "Name": "Model Identification and Data Fitting",
            "ProgID": "MAAIDSDM",
            "RoomID": "BOU 1.001",
            "Lecturers": "P.Bonizzi;R.Peeters"
        }
	],
	"2019-11-28 11:00:00": [
		{
            "CourseID": "KEN3440",
            "Name": "Introduction to Bio-Informatics",
            "ProgID": "BAY3",
            "RoomID": "BOU 0.015",
            "Lecturers": "R.Cavill"
        },
		{
            "CourseID": "KEN4242",
            "Name": "Model Identification and Data Fitting",
            "ProgID": "MAAIDSDM",
            "RoomID": "BOU 1.001",
            "Lecturers": "P.Bonizzi;R.Peeters"
        }
	],
	"2019-11-28 13:30:00": [
		{
            "CourseID": "KEN1410",
            "Name": "Linear Algebra",
            "ProgID": "BAY1",
            "RoomID": "TAPB 0.009",
            "Lecturers": "P.Bonizzi;S.Mehrkanoon"
        },
		{
            "CourseID": "KEN3150",
            "Name": "Software and Systems Verifications",
            "ProgID": "BAY3",
            "RoomID": "BOU 0.015",
            "Lecturers": "P.Collins"
        },
		{
            "CourseID": "KEN4245",
            "Name": "Information Security",
            "ProgID": "MAAIDSDM",
            "RoomID": "BOU 2.015",
            "Lecturers": "A.Zarras"
        }
	],
	"2019-11-28 16:00:00": [
		{
            "CourseID": "KEN1410",
            "Name": "Linear Algebra",
            "ProgID": "BAY1",
            "RoomID": "TAPB 0.009",
            "Lecturers": "P.Bonizzi;S.Mehrkanoon"
        },
		{
            "CourseID": "KEN3231",
            "Name": "Logic for Artificial Intelligence",
            "ProgID": "BAY3",
            "RoomID": "BOU 0.015",
            "Lecturers": "N.Roos"
        },
		{
            "CourseID": "KEN4244",
            "Name": "Applications of Image & Video Processing",
            "ProgID": "MAAIDSDM",
            "RoomID": "BOU 2.015",
            "Lecturers": "A.Briassouli"
        }
	],

	"2019-11-29 08:30:00": [
		{
            "CourseID": "KEN1220",
            "Name": "Introduction to Computer Science 2",
            "ProgID": "BAY1",
            "RoomID": "TAPB 0.009",
            "Lecturers": "E.Smirnov;A.Zarras"
        },
		{
            "CourseID": "KEN3235",
            "Name": "Parallel Programming",
            "ProgID": "BAY3",
            "RoomID": "BOU 0.015",
            "Lecturers": "H.Pflug;B.Küppers;C.Terboven"
        }
	],
	"2019-11-29 11:00:00": [
		{
            "CourseID": "KEN1220",
            "Name": "Introduction to Computer Science 2",
            "ProgID": "BAY1",
            "RoomID": "TAPB 0.009",
            "Lecturers": "E.Smirnov;A.Zarras"
        },
		{
            "CourseID": "KEN2220",
            "Name": "Graph Theory",
            "ProgID": "BAY2",
            "RoomID": "TAPZ 0.011",
            "Lecturers": "M.Mihalak"
        },
		{
            "CourseID": "KEN3235",
            "Name": "Parallel Programming",
            "ProgID": "BAY3",
            "RoomID": "BOU 0.015",
            "Lecturers": "H.Pflug;B.Küppers;C.Terboven"
        },
		{
            "CourseID": "KEN4245",
            "Name": "Information Security",
            "ProgID": "MAAIDSDM",
            "RoomID": "BOU 2.015",
            "Lecturers": "A.Zarras"
        }
	],
	"2019-11-29 13:30:00": [
		{
            "CourseID": "KEN1220",
            "Name": "Introduction to Computer Science 2",
            "ProgID": "BAY1",
            "RoomID": "TAPB 0.009",
            "Lecturers": "E.Smirnov;A.Zarras"
        },
		{
            "CourseID": "KEN2220",
            "Name": "Graph Theory",
            "ProgID": "BAY2",
            "RoomID": "TAPZ 0.011",
            "Lecturers": "M.Mihalak"
        },
		{
            "CourseID": "KEN3235",
            "Name": "Parallel Programming",
            "ProgID": "BAY3",
            "RoomID": "BOU 0.015",
            "Lecturers": "H.Pflug;B.Küppers;C.Terboven"
        },
		{
            "CourseID": "KEN4245",
            "Name": "Information Security",
            "ProgID": "MAAIDSDM",
            "RoomID": "BOU 2.015",
            "Lecturers": "A.Zarras"
        }
	],
	"2019-11-29 16:00:00": [
		{
            "CourseID": "KEN3231",
            "Name": "Logic for Artificial Intelligence",
            "ProgID": "BAY3",
            "RoomID": "BOU 0.015",
            "Lecturers": "N.Roos"
        }
	],




	"2019-12-02 08:30:00": [
		{
            "CourseID": "KEN1220",
            "Name": "Introduction to Computer Science 2",
            "ProgID": "BAY1",
            "RoomID": "TAPB 0.009",
            "Lecturers": "E.Smirnov;A.Zarras"
        },
		{
            "CourseID": "KEN1410",
            "Name": "Linear Algebra",
            "ProgID": "BAY1",
            "RoomID": "TAPB 0.004",
            "Lecturers": "P.Bonizzi;S.Mehrkanoon"
        },
		{
            "CourseID": "KEN3237",
            "Name": "Web Applications",
            "ProgID": "BAY3",
            "RoomID": "BOU 0.015",
            "Lecturers": "T.Dondorf"
        }
	],
	"2019-12-02 11:00:00": [
		{
            "CourseID": "KEN1220",
            "Name": "Introduction to Computer Science 2",
            "ProgID": "BAY1",
            "RoomID": "TAPB 0.004",
            "Lecturers": "E.Smirnov;A.Zarras"
        },
		{
            "CourseID": "KEN1410",
            "Name": "Linear Algebra",
            "ProgID": "BAY1",
            "RoomID": "TAPB 0.009",
            "Lecturers": "P.Bonizzi;S.Mehrkanoon"
        },
		{
            "CourseID": "KEN2230",
            "Name": "Reasoning Techniques",
            "ProgID": "BAY2",
            "RoomID": "TAPZ 0.011",
            "Lecturers": "J.Uiterwijk"
        },
		{
            "CourseID": "KEN3237",
            "Name": "Web Applications",
            "ProgID": "BAY3",
            "RoomID": "BOU 0.015",
            "Lecturers": "T.Dondorf"
        },
		{
            "CourseID": "KEN4111",
            "Name": "Multi-Agent Systems",
            "ProgID": "MAAIDSDM",
            "RoomID": "BOU 1.001",
            "Lecturers": "G.Weiss"
        }
	],
	"2019-12-02 13:30:00": [
		{
            "CourseID": "KEN1210",
            "Name": "Computational and Cognitive Neuroscience",
            "ProgID": "BAY1",
            "RoomID": "Pathe Hall 8",
            "Lecturers": "A.Roebroeck;M.Capalbo"
        },
		{
            "CourseID": "KEN2220",
            "Name": "Graph Theory",
            "ProgID": "BAY2",
            "RoomID": "TAPZ 0.011",
            "Lecturers": "M.Mihalak"
        },
		{
            "CourseID": "KEN3237",
            "Name": "Web Applications",
            "ProgID": "BAY3",
            "RoomID": "BOU 0.015",
            "Lecturers": "T.Dondorf"
        },
		{
            "CourseID": "KEN4111",
            "Name": "Multi-Agent Systems",
            "ProgID": "MAAIDSDM",
            "RoomID": "BOU 1.001",
            "Lecturers": "G.Weiss"
        }
	],
	"2019-12-02 16:00:00": [
		{
            "CourseID": "KEN1300-1",
            "Name": "Project Meeting",
            "ProgID": "BAY1",
            "RoomID": "BOU 0.009",
            "Lecturers": "K.Schüller;M.Popa;C.Sironi"
        },
		{
            "CourseID": "KEN2240",
            "Name": "Machine Learning",
            "ProgID": "BAY2",
            "RoomID": "TAPZ 0.011",
            "Lecturers": "E.Smirnov;R.Möckel;E.Hortal"
        },
		{
            "CourseID": "KEN3231",
            "Name": "Logic for Artificial Intelligence",
            "ProgID": "BAY3",
            "RoomID": "BOU 0.015",
            "Lecturers": "N.Roos"
        }
	],

	"2019-12-03 08:30:00": [
		{
            "CourseID": "KEN1210",
            "Name": "Computational and Cognitive Neuroscience",
            "ProgID": "BAY1",
            "RoomID": "Pathe Hall 7",
            "Lecturers": "A.Roebroeck;M.Capalbo"
        },
		{
            "CourseID": "KEN4244",
            "Name": "Applications of Image & Video Processing",
            "ProgID": "MAAIDSDM",
            "RoomID": "BOU 2.015",
            "Lecturers": "A.Briassouli"
        }
	],
	"2019-12-03 11:00:00": [
		{
            "CourseID": "KEN2230",
            "Name": "Reasoning Techniques",
            "ProgID": "BAY2",
            "RoomID": "TAPZ 0.011",
            "Lecturers": "J.Uiterwijk"
        },
		{
            "CourseID": "KEN3150",
            "Name": "Software and Systems Verifications",
            "ProgID": "BAY3",
            "RoomID": "BOU 0.015",
            "Lecturers": "P.Collins"
        },
		{
            "CourseID": "KEN4244",
            "Name": "Applications of Image & Video Processing",
            "ProgID": "MAAIDSDM",
            "RoomID": "BOU 2.015",
            "Lecturers": "A.Briassouli"
        }
	],
	"2019-12-03 13:30:00": [
		{
            "CourseID": "KEN1300-1",
            "Name": "Project Meeting",
            "ProgID": "BAY1",
            "RoomID": "BOU 2.002",
            "Lecturers": "K.Schüller;M.Popa;C.Sironi"
        },
		{
            "CourseID": "KEN2240",
            "Name": "Machine Learning",
            "ProgID": "BAY2",
            "RoomID": "TAPZ 0.011",
            "Lecturers": "E.Smirnov;R.Möckel;E.Hortal"
        },
		{
            "CourseID": "KEN3150",
            "Name": "Software and Systems Verifications",
            "ProgID": "BAY3",
            "RoomID": "BOU 0.015",
            "Lecturers": "P.Collins"
        },
		{
            "CourseID": "KEN4242",
            "Name": "Model Identification and Data Fitting",
            "ProgID": "MAAIDSDM",
            "RoomID": "BOU 1.001",
            "Lecturers": "P.Bonizzi;R.Peeters"
        }
	],
	"2019-12-03 16:00:00": [
		{
            "CourseID": "KEN1300-1",
            "Name": "Project Meeting",
            "ProgID": "BAY1",
            "RoomID": "BOU 2.002",
            "Lecturers": "K.Schüller;M.Popa;C.Sironi"
        },
		{
            "CourseID": "KEN2240",
            "Name": "Machine Learning",
            "ProgID": "BAY2",
            "RoomID": "TAPZ 0.011",
            "Lecturers": "E.Smirnov;R.Möckel;E.Hortal"
        },
		{
            "CourseID": "KEN4242",
            "Name": "Model Identification and Data Fitting",
            "ProgID": "MAAIDSDM",
            "RoomID": "BOU 1.001",
            "Lecturers": "P.Bonizzi;R.Peeters"
        }
	],

	"2019-12-04 08:30:00": [
		{
            "CourseID": "KEN1410",
            "Name": "Linear Algebra",
            "ProgID": "BAY1",
            "RoomID": "TAPB 0.009",
            "Lecturers": "P.Bonizzi;S.Mehrkanoon"
        },
		{
            "CourseID": "KEN3300-3",
            "Name": "Project Skills: CV workshop",
            "ProgID": "BAY3",
            "RoomID": "BON B1.15",
            "Lecturers": "SSC"
        }
	],
	"2019-12-04 11:00:00": [
		{
            "CourseID": "KEN1410",
            "Name": "Linear Algebra",
            "ProgID": "BAY1",
            "RoomID": "TAPB 0.009",
            "Lecturers": "P.Bonizzi;S.Mehrkanoon"
        },
		{
            "CourseID": "KEN2300-1",
            "Name": "Project Meeting",
            "ProgID": "BAY2",
            "RoomID": "BOU 2.015",
            "Lecturers": "K.Schüller"
        },
		{
            "CourseID": "KEN4154",
            "Name": "Advanced Concepts in Machine Learning",
            "ProgID": "MAAIDSDM",
            "RoomID": "TAPZ 0.011",
            "Lecturers": "K.Driessens;D.Rafailidis"
        }
	],
	"2019-12-04 13:30:00": [
		{
            "CourseID": "KEN1410",
            "Name": "Linear Algebra",
            "ProgID": "BAY1",
            "RoomID": "TAPB 0.009",
            "Lecturers": "P.Bonizzi;S.Mehrkanoon"
        },
		{
            "CourseID": "KEN2300-1",
            "Name": "Project Meeting",
            "ProgID": "BAY2",
            "RoomID": "BOU 2.015",
            "Lecturers": "K.Schüller"
        },
		{
            "CourseID": "KEN4154",
            "Name": "Advanced Concepts in Machine Learning",
            "ProgID": "MAAIDSDM",
            "RoomID": "TAPZ 0.011",
            "Lecturers": "K.Driessens;D.Rafailidis"
        }
	],
	"2019-12-04 16:00:00": [
		{
            "CourseID": "KEN1410",
            "Name": "Linear Algebra",
            "ProgID": "BAY1",
            "RoomID": "TAPB 0.009",
            "Lecturers": "P.Bonizzi;S.Mehrkanoon"
        },
		{
            "CourseID": "KEN3300-1",
            "Name": "Project Meeting",
            "ProgID": "BAY3",
            "RoomID": "BOU 0.015",
            "Lecturers": "R.Möckel"
        },
		{
            "CourseID": "KEN4111",
            "Name": "Multi-Agent Systems",
            "ProgID": "MAAIDSDM",
            "RoomID": "BOU 1.001",
            "Lecturers": "G.Weiss"
        }
	],

	"2019-12-05 08:30:00": [
		{
            "CourseID": "KEN1410",
            "Name": "Linear Algebra",
            "ProgID": "BAY1",
            "RoomID": "TAPB 0.004",
            "Lecturers": "P.Bonizzi;S.Mehrkanoon"
        },
		{
            "CourseID": "KEN1300-2",
            "Name": "Project Skills: Elementary Writing & Presenting",
            "ProgID": "BAY1",
            "RoomID": "TAPB 0.009",
            "Lecturers": "K.Schüller"
        },
		{
            "CourseID": "KEN3440",
            "Name": "Introduction to Bio-Informatics",
            "ProgID": "BAY3",
            "RoomID": "BOU 0.015",
            "Lecturers": "R.Cavill"
        },
		{
            "CourseID": "KEN4242",
            "Name": "Model Identification and Data Fitting",
            "ProgID": "MAAIDSDM",
            "RoomID": "BOU 1.001",
            "Lecturers": "P.Bonizzi;R.Peeters"
        }
	],
	"2019-12-05 11:00:00": [
		{
            "CourseID": "KEN1410",
            "Name": "Linear Algebra",
            "ProgID": "BAY1",
            "RoomID": "TAPB 0.009",
            "Lecturers": "P.Bonizzi;S.Mehrkanoon"
        },
		{
            "CourseID": "KEN1300-2",
            "Name": "Project Skills: Elementary Writing & Presenting",
            "ProgID": "BAY1",
            "RoomID": "TAPB 0.004",
            "Lecturers": "K.Schüller"
        },
		{
            "CourseID": "KEN3440",
            "Name": "Introduction to Bio-Informatics",
            "ProgID": "BAY3",
            "RoomID": "BOU 0.015",
            "Lecturers": "R.Cavill"
        },
		{
            "CourseID": "KEN4242",
            "Name": "Model Identification and Data Fitting",
            "ProgID": "MAAIDSDM",
            "RoomID": "BOU 1.001",
            "Lecturers": "P.Bonizzi;R.Peeters"
        }
	],
	"2019-12-05 13:30:00": [
		{
            "CourseID": "KEN1220",
            "Name": "Introduction to Computer Science 2",
            "ProgID": "BAY1",
            "RoomID": "TAPB 0.009",
            "Lecturers": "E.Smirnov;A.Zarras"
        },
		{
            "CourseID": "KEN3150",
            "Name": "Software and Systems Verifications",
            "ProgID": "BAY3",
            "RoomID": "BOU 0.015",
            "Lecturers": "P.Collins"
        },
		{
            "CourseID": "KEN4245",
            "Name": "Information Security",
            "ProgID": "MAAIDSDM",
            "RoomID": "BOU 2.015",
            "Lecturers": "A.Zarras"
        }
	],
	"2019-12-05 16:00:00": [
		{
            "CourseID": "KEN1220",
            "Name": "Introduction to Computer Science 2",
            "ProgID": "BAY1",
            "RoomID": "TAPB 0.009",
            "Lecturers": "E.Smirnov;A.Zarras"
        },
		{
            "CourseID": "KEN3231",
            "Name": "Logic for Artificial Intelligence",
            "ProgID": "BAY3",
            "RoomID": "BOU 0.015",
            "Lecturers": "N.Roos"
        },
		{
            "CourseID": "KEN4244",
            "Name": "Applications of Image & Video Processing",
            "ProgID": "MAAIDSDM",
            "RoomID": "BOU 2.015",
            "Lecturers": "A.Briassouli"
        }
	],

	"2019-12-06 08:30:00": [
		{
            "CourseID": "KEN1220",
            "Name": "Introduction to Computer Science 2",
            "ProgID": "BAY1",
            "RoomID": "TAPB 0.009",
            "Lecturers": "E.Smirnov;A.Zarras"
        },
		{
            "CourseID": "KEN3235",
            "Name": "Parallel Programming",
            "ProgID": "BAY3",
            "RoomID": "BOU 0.015",
            "Lecturers": "H.Pflug;B.Küppers;C.Terboven"
        },
		{
            "CourseID": "KEN4130-4230",
            "Name": "Presentation Second Phase AI & DSDM",
            "ProgID": "MAAIDSDM",
            "RoomID": "BOU 2.015",
            "Lecturers": "K.Driessens;N.Roos;G.Spanakis;J.Uiterwijk;G.Weiss;P.Bonizzi;A.Briassouli;C.Browne;R.Cavill;P.Collins;J.Karel;G.Schoenmakers;E.Smirnov;K.Stankova;F.Thuijsman;M.Winands"
        }
	],
	"2019-12-06 11:00:00": [
		{
            "CourseID": "KEN1220",
            "Name": "Introduction to Computer Science 2",
            "ProgID": "BAY1",
            "RoomID": "TAPB 0.009",
            "Lecturers": "E.Smirnov;A.Zarras"
        },
		{
            "CourseID": "KEN2220",
            "Name": "Graph Theory",
            "ProgID": "BAY2",
            "RoomID": "TAPZ 0.011",
            "Lecturers": "M.Mihalak"
        },
		{
            "CourseID": "KEN3235",
            "Name": "Parallel Programming",
            "ProgID": "BAY3",
            "RoomID": "BOU 0.015",
            "Lecturers": "H.Pflug;B.Küppers;C.Terboven"
        },
		{
            "CourseID": "KEN4130-4230",
            "Name": "Presentation Second Phase AI & DSDM",
            "ProgID": "MAAIDSDM",
            "RoomID": "BOU 2.015",
            "Lecturers": "K.Driessens;N.Roos;G.Spanakis;J.Uiterwijk;G.Weiss;P.Bonizzi;A.Briassouli;C.Browne;R.Cavill;P.Collins;J.Karel;G.Schoenmakers;E.Smirnov;K.Stankova;F.Thuijsman;M.Winands"
        }
	],
	"2019-12-06 13:30:00": [
		{
            "CourseID": "KEN1220",
            "Name": "Introduction to Computer Science 2",
            "ProgID": "BAY1",
            "RoomID": "TAPB 0.009",
            "Lecturers": "E.Smirnov;A.Zarras"
        },
		{
            "CourseID": "KEN2220",
            "Name": "Graph Theory",
            "ProgID": "BAY2",
            "RoomID": "TAPZ 0.011",
            "Lecturers": "M.Mihalak"
        },
		{
            "CourseID": "KEN3235",
            "Name": "Parallel Programming",
            "ProgID": "BAY3",
            "RoomID": "BOU 0.015",
            "Lecturers": "H.Pflug;B.Küppers;C.Terboven"
        },
		{
            "CourseID": "KEN4130-4230",
            "Name": "Presentation Second Phase AI & DSDM",
            "ProgID": "MAAIDSDM",
            "RoomID": "BOU 2.015",
            "Lecturers": "K.Driessens;N.Roos;G.Spanakis;J.Uiterwijk;G.Weiss;P.Bonizzi;A.Briassouli;C.Browne;R.Cavill;P.Collins;J.Karel;G.Schoenmakers;E.Smirnov;K.Stankova;F.Thuijsman;M.Winands"
        }
	],
	"2019-12-06 16:00:00": [
		{
            "CourseID": "KEN3231",
            "Name": "Logic for Artificial Intelligence",
            "ProgID": "BAY3",
            "RoomID": "BOU 0.015",
            "Lecturers": "N.Roos"
        },
		{
            "CourseID": "KEN4130-4230",
            "Name": "Presentation Second Phase AI & DSDM",
            "ProgID": "MAAIDSDM",
            "RoomID": "BOU 2.015",
            "Lecturers": "K.Driessens;N.Roos;G.Spanakis;J.Uiterwijk;G.Weiss;P.Bonizzi;A.Briassouli;C.Browne;R.Cavill;P.Collins;J.Karel;G.Schoenmakers;E.Smirnov;K.Stankova;F.Thuijsman;M.Winands"
        }
	],




	"2019-12-09 08:30:00": [
		{
            "CourseID": "KEN1220",
            "Name": "Introduction to Computer Science 2",
            "ProgID": "BAY1",
            "RoomID": "TAPB 0.009",
            "Lecturers": "E.Smirnov;A.Zarras"
        },
		{
            "CourseID": "KEN1410",
            "Name": "Linear Algebra",
            "ProgID": "BAY1",
            "RoomID": "TAPB 0.004",
            "Lecturers": "P.Bonizzi;S.Mehrkanoon"
        },
		{
            "CourseID": "KEN3237",
            "Name": "Web Applications",
            "ProgID": "BAY3",
            "RoomID": "BOU 0.015",
            "Lecturers": "T.Dondorf"
        }
	],
	"2019-12-09 11:00:00": [
		{
            "CourseID": "KEN1220",
            "Name": "Introduction to Computer Science 2",
            "ProgID": "BAY1",
            "RoomID": "TAPB 0.004",
            "Lecturers": "E.Smirnov;A.Zarras"
        },
		{
            "CourseID": "KEN1410",
            "Name": "Linear Algebra",
            "ProgID": "BAY1",
            "RoomID": "TAPB 0.009",
            "Lecturers": "P.Bonizzi;S.Mehrkanoon"
        },
		{
            "CourseID": "KEN2230",
            "Name": "Reasoning Techniques",
            "ProgID": "BAY2",
            "RoomID": "TAPZ 0.011",
            "Lecturers": "J.Uiterwijk"
        },
		{
            "CourseID": "KEN3237",
            "Name": "Web Applications",
            "ProgID": "BAY3",
            "RoomID": "BOU 0.015",
            "Lecturers": "T.Dondorf"
        },
		{
            "CourseID": "KEN4111",
            "Name": "Multi-Agent Systems",
            "ProgID": "MAAIDSDM",
            "RoomID": "BOU 1.001",
            "Lecturers": "G.Weiss"
        }
	],
	"2019-12-09 13:30:00": [
		{
            "CourseID": "KEN2220",
            "Name": "Graph Theory",
            "ProgID": "BAY2",
            "RoomID": "TAPZ 0.011",
            "Lecturers": "M.Mihalak"
        },
		{
            "CourseID": "KEN3237",
            "Name": "Web Applications",
            "ProgID": "BAY3",
            "RoomID": "BOU 0.015",
            "Lecturers": "T.Dondorf"
        },
		{
            "CourseID": "KEN4111",
            "Name": "Multi-Agent Systems",
            "ProgID": "MAAIDSDM",
            "RoomID": "BOU 1.001",
            "Lecturers": "G.Weiss"
        }
	],
	"2019-12-09 16:00:00": [
		{
            "CourseID": "KEN2240",
            "Name": "Machine Learning",
            "ProgID": "BAY2",
            "RoomID": "TAPZ 0.011",
            "Lecturers": "E.Smirnov;R.Möckel;E.Hortal"
        },
		{
            "CourseID": "KEN3440",
            "Name": "Introduction to Bio-Informatics",
            "ProgID": "BAY3",
            "RoomID": "BOU 0.015",
            "Lecturers": "R.Cavill"
        }
	],

	"2019-12-10 08:30:00": [
		{
            "CourseID": "KEN1210",
            "Name": "Computational and Cognitive Neuroscience",
            "ProgID": "BAY1",
            "RoomID": "Pathe Hall 8",
            "Lecturers": "A.Roebroeck;M.Capalbo"
        },
		{
            "CourseID": "KEN2230",
            "Name": "Reasoning Techniques",
            "ProgID": "BAY2",
            "RoomID": "TAPZ 0.011",
            "Lecturers": "J.Uiterwijk"
        },
		{
            "CourseID": "KEN3150",
            "Name": "Software and Systems Verifications",
            "ProgID": "BAY3",
            "RoomID": "BOU 0.015",
            "Lecturers": "P.Collins"
        },
		{
            "CourseID": "KEN4244",
            "Name": "Applications of Image & Video Processing",
            "ProgID": "MAAIDSDM",
            "RoomID": "BOU 2.015",
            "Lecturers": "A.Briassouli"
        }
	],
	"2019-12-10 11:00:00": [
		{
            "CourseID": "KEN1300-1",
            "Name": "Project Meeting",
            "ProgID": "BAY1",
            "RoomID": "BOU 0.009",
            "Lecturers": "K.Schüller;M.Popa;C.Sironi"
        },
		{
            "CourseID": "KEN2230",
            "Name": "Reasoning Techniques",
            "ProgID": "BAY2",
            "RoomID": "TAPZ 0.011",
            "Lecturers": "J.Uiterwijk"
        },
		{
            "CourseID": "KEN3150",
            "Name": "Software and Systems Verifications",
            "ProgID": "BAY3",
            "RoomID": "BOU 0.015",
            "Lecturers": "P.Collins"
        },
		{
            "CourseID": "KEN4244",
            "Name": "Applications of Image & Video Processing",
            "ProgID": "MAAIDSDM",
            "RoomID": "BOU 2.015",
            "Lecturers": "A.Briassouli"
        }
	],
	"2019-12-10 13:30:00": [
		{
            "CourseID": "KEN1300-1",
            "Name": "Project Meeting",
            "ProgID": "BAY1",
            "RoomID": "BOU 0.009",
            "Lecturers": "K.Schüller;M.Popa;C.Sironi"
        },
		{
            "CourseID": "KEN2240",
            "Name": "Machine Learning",
            "ProgID": "BAY2",
            "RoomID": "TAPZ 0.011",
            "Lecturers": "E.Smirnov;R.Möckel;E.Hortal"
        },
		{
            "CourseID": "KEN4242",
            "Name": "Model Identification and Data Fitting",
            "ProgID": "MAAIDSDM",
            "RoomID": "BOU 1.001",
            "Lecturers": "P.Bonizzi;R.Peeters"
        }
	],
	"2019-12-10 16:00:00": [
		{
            "CourseID": "KEN1300-1",
            "Name": "Project Meeting",
            "ProgID": "BAY1",
            "RoomID": "BOU 0.009",
            "Lecturers": "K.Schüller;M.Popa;C.Sironi"
        }
	],

	"2019-12-11 08:30:00": [
		{
            "CourseID": "KEN1410",
            "Name": "Linear Algebra",
            "ProgID": "BAY1",
            "RoomID": "TAPB 0.009",
            "Lecturers": "P.Bonizzi;S.Mehrkanoon"
        },
		{
            "CourseID": "KEN4154",
            "Name": "Advanced Concepts in Machine Learning",
            "ProgID": "MAAIDSDM",
            "RoomID": "TAPZ 0.011",
            "Lecturers": "K.Driessens;D.Rafailidis"
        }
	],
	"2019-12-11 11:00:00": [
		{
            "CourseID": "KEN1410",
            "Name": "Linear Algebra",
            "ProgID": "BAY1",
            "RoomID": "TAPB 0.009",
            "Lecturers": "P.Bonizzi;S.Mehrkanoon"
        },
		{
            "CourseID": "KEN4154",
            "Name": "Advanced Concepts in Machine Learning",
            "ProgID": "MAAIDSDM",
            "RoomID": "TAPZ 0.011",
            "Lecturers": "K.Driessens;D.Rafailidis"
        }
	],
	"2019-12-11 13:30:00": [

	],
	"2019-12-11 16:00:00": [

	],

	"2019-12-12 08:30:00": [
		{
            "CourseID": "KEN1220",
            "Name": "Introduction to Computer Science 2",
            "ProgID": "BAY1",
            "RoomID": "TAPB 0.009",
            "Lecturers": "E.Smirnov;A.Zarras"
        },
		{
            "CourseID": "KEN2300-2",
            "Name": "Presentation Second Phase",
            "ProgID": "BAY2",
            "RoomID": "TAPZ 0.011",
            "Lecturers": "K.Schüller;M.Mihalak;J.Uiterwijk"
        },
		{
            "CourseID": "KEN3440",
            "Name": "Introduction to Bio-Informatics",
            "ProgID": "BAY3",
            "RoomID": "BOU 0.015",
            "Lecturers": "R.Cavill"
        }
	],
	"2019-12-12 11:00:00": [
		{
            "CourseID": "KEN1220",
            "Name": "Introduction to Computer Science 2",
            "ProgID": "BAY1",
            "RoomID": "TAPB 0.009",
            "Lecturers": "E.Smirnov;A.Zarras"
        },
		{
            "CourseID": "KEN2300-2",
            "Name": "Presentation Second Phase",
            "ProgID": "BAY2",
            "RoomID": "TAPZ 0.011",
            "Lecturers": "K.Schüller;M.Mihalak;J.Uiterwijk"
        },
		{
            "CourseID": "KEN3440",
            "Name": "Introduction to Bio-Informatics",
            "ProgID": "BAY3",
            "RoomID": "BOU 0.015",
            "Lecturers": "R.Cavill"
        }
	],
	"2019-12-12 13:30:00": [
		{
            "CourseID": "KEN3231",
            "Name": "Logic for Artificial Intelligence",
            "ProgID": "BAY3",
            "RoomID": "BOU 0.015",
            "Lecturers": "N.Roos"
        }
	],
	"2019-12-12 16:00:00": [

	],

	"2019-12-13 08:30:00": [
		{
            "CourseID": "KEN1300-3",
            "Name": "Presentation Second Phase",
            "ProgID": "BAY1",
            "RoomID": "BOU 2.002",
            "Lecturers": "P.Bonizzi;E.Hortal;S.Kelk;S.Mehrkanoon;J.Niehues;E.Smirnov"
        },
		{
            "CourseID": "KEN3231",
            "Name": "Logic for Artificial Intelligence",
            "ProgID": "BAY3",
            "RoomID": "BOU 0.015",
            "Lecturers": "N.Roos"
        },
		{
            "CourseID": "KEN4245",
            "Name": "Information Security",
            "ProgID": "MAAIDSDM",
            "RoomID": "BOU 2.015",
            "Lecturers": "A.Zarras"
        }
	],
	"2019-12-13 11:00:00": [
		{
            "CourseID": "KEN1300-3",
            "Name": "Presentation Second Phase",
            "ProgID": "BAY1",
            "RoomID": "BOU 2.002",
            "Lecturers": "P.Bonizzi;E.Hortal;S.Kelk;S.Mehrkanoon;J.Niehues;E.Smirnov"
        },
		{
            "CourseID": "KEN3231",
            "Name": "Logic for Artificial Intelligence",
            "ProgID": "BAY3",
            "RoomID": "BOU 0.015",
            "Lecturers": "N.Roos"
        },
		{
            "CourseID": "KEN4245",
            "Name": "Information Security",
            "ProgID": "MAAIDSDM",
            "RoomID": "BOU 2.015",
            "Lecturers": "A.Zarras"
        }
	],
	"2019-12-13 13:30:00": [
		{
            "CourseID": "KEN1300-3",
            "Name": "Presentation Second Phase",
            "ProgID": "BAY1",
            "RoomID": "BOU 2.002",
            "Lecturers": "P.Bonizzi;E.Hortal;S.Kelk;S.Mehrkanoon;J.Niehues;E.Smirnov"
        },
		{
            "CourseID": "KEN2220",
            "Name": "Graph Theory",
            "ProgID": "BAY2",
            "RoomID": "TAPZ 0.011",
            "Lecturers": "M.Mihalak"
        },
		{
            "CourseID": "KEN3300-2",
            "Name": "Presentation Second Phase",
            "ProgID": "BAY3",
            "RoomID": "BOU 0.015",
            "Lecturers": "R.Möckel;A.Briassouli"
        }
	],
	"2019-12-13 16:00:00": [
		{
            "CourseID": "KEN3300-2",
            "Name": "Presentation Second Phase",
            "ProgID": "BAY3",
            "RoomID": "BOU 0.015",
            "Lecturers": "R.Möckel;A.Briassouli"
        }
	]
}